<?xml version="1.0" encoding="utf-8"?>
<Prices>
  <ChainID>7290696200003</ChainID>
  <SubChainID>001</SubChainID>
  <StoreID>065</StoreID>
  <BikoretNo>000</BikoretNo>
  <Products>
    <Product>
      <PriceUpdateDate>2018/11/25 08:15</PriceUpdateDate>
      <ItemCode>23489</ItemCode>
      <ItemType>0</ItemType>
      <ItemName>דג סלמון נורבגי טרי שלם - נקי</ItemName>
      <ManufactureName>מאסטרפוד בעמ</ManufactureName>
      <ManufactureCountry />
      <ManufactureItemDescription />
      <UnitQty>ק"ג</UnitQty>
      <Quantity>1</Quantity>
      <UnitMeasure>100 גרם</UnitMeasure>
      <BisWeighted>1</BisWeighted>
      <QtyInPackage>1</QtyInPackage>
      <ItemPrice>59.90</ItemPrice>
      <UnitOfMeasurePrice>59.90</UnitOfMeasurePrice>
      <AllowDiscount>1</AllowDiscount>
      <itemStatus>1</itemStatus>
      <LastUpdateDate />
      <LastUpdateTime />
    </Product>
    <Product>
      <PriceUpdateDate>2019/08/29 16:39</PriceUpdateDate>
      <ItemCode>372204</ItemCode>
      <ItemType>0</ItemType>
      <ItemName>דג ברמונדי נקי שלם</ItemName>
      <ManufactureName>מאסטרפוד בעמ</ManufactureName>
      <ManufactureCountry />
      <ManufactureItemDescription />
      <UnitQty>ק"ג</UnitQty>
      <Quantity>1</Quantity>
      <UnitMeasure />
      <BisWeighted>1</BisWeighted>
      <QtyInPackage>1</QtyInPackage>
      <ItemPrice>49.90</ItemPrice>
      <UnitOfMeasurePrice>49.90</UnitOfMeasurePrice>
      <AllowDiscount>1</AllowDiscount>
      <itemStatus>1</itemStatus>
      <LastUpdateDate />
      <LastUpdateTime />
    </Product>
    <Product>
      <PriceUpdateDate>2019/12/22 10:21</PriceUpdateDate>
      <ItemCode>571515</ItemCode>
      <ItemType>0</ItemType>
      <ItemName>פילה סלמון נורבגי שלם -טרי</ItemName>
      <ManufactureName>מאסטרפוד בעמ</ManufactureName>
      <ManufactureCountry />
      <ManufactureItemDescription />
      <UnitQty>ק"ג</UnitQty>
      <Quantity>10</Quantity>
      <UnitMeasure>100 גרם</UnitMeasure>
      <BisWeighted>1</BisWeighted>
      <QtyInPackage>1</QtyInPackage>
      <ItemPrice>99</ItemPrice>
      <UnitOfMeasurePrice>9.90</UnitOfMeasurePrice>
      <AllowDiscount>1</AllowDiscount>
      <itemStatus>1</itemStatus>
      <LastUpdateDate />
      <LastUpdateTime />
    </Product>
    <Product>
      <PriceUpdateDate>2020/03/16 10:59</PriceUpdateDate>
      <ItemCode>2206019</ItemCode>
      <ItemType>0</ItemType>
      <ItemName>כרעיים עוף טרי ארוז</ItemName>
      <ManufactureName>טל הל יסכה בעמ</ManufactureName>
      <ManufactureCountry />
      <ManufactureItemDescription />
      <UnitQty>ק"ג</UnitQty>
      <Quantity>1</Quantity>
      <UnitMeasure />
      <BisWeighted>1</BisWeighted>
      <QtyInPackage>1</QtyInPackage>
      <ItemPrice>26.90</ItemPrice>
      <UnitOfMeasurePrice>26.90</UnitOfMeasurePrice>
      <AllowDiscount>1</AllowDiscount>
      <itemStatus>1</itemStatus>
      <LastUpdateDate />
      <LastUpdateTime />
    </Product>
    <Product>
      <PriceUpdateDate>2020/03/16 10:59</PriceUpdateDate>
      <ItemCode>2206026</ItemCode>
      <ItemType>0</ItemType>
      <ItemName>ירך עוף טרי ארוז</ItemName>
      <ManufactureName>עוף עוז שיווק בעמ</ManufactureName>
      <ManufactureCountry />
      <ManufactureItemDescription />
      <UnitQty>ק"ג</UnitQty>
      <Quantity>1</Quantity>
      <UnitMeasure />
      <BisWeighted>1</BisWeighted>
      <QtyInPackage>1</QtyInPackage>
      <ItemPrice>26.90</ItemPrice>
      <UnitOfMeasurePrice>26.90</UnitOfMeasurePrice>
      <AllowDiscount>1</AllowDiscount>
      <itemStatus>1</itemStatus>
      <LastUpdateDate />
      <LastUpdateTime />
    </Product>
    <Product>
      <PriceUpdateDate>2019/11/13 08:21</PriceUpdateDate>
      <ItemCode>2206101</ItemCode>
      <ItemType>0</ItemType>
      <ItemName>סטייק פרגית ללא עור</ItemName>
      <ManufactureName>טל הל יסכה בעמ</ManufactureName>
      <ManufactureCountry />
      <ManufactureItemDescription />
      <UnitQty>ק"ג</UnitQty>
      <Quantity>1</Quantity>
      <UnitMeasure />
      <BisWeighted>1</BisWeighted>
      <QtyInPackage>1</QtyInPackage>
      <ItemPrice>44.90</ItemPrice>
      <UnitOfMeasurePrice>44.90</UnitOfMeasurePrice>
      <AllowDiscount>1</AllowDiscount>
      <itemStatus>1</itemStatus>
      <LastUpdateDate />
      <LastUpdateTime />
    </Product>
    <Product>
      <PriceUpdateDate>2020/04/30 07:49</PriceUpdateDate>
      <ItemCode>608614255504</ItemCode>
      <ItemType>0</ItemType>
      <ItemName>פופקורנס טעם בצל 50 גר</ItemName>
      <ManufactureName>אבאל יזמות בעמ</ManufactureName>
      <ManufactureCountry />
      <ManufactureItemDescription />
      <UnitQty>יח`</UnitQty>
      <Quantity>0.50</Quantity>
      <UnitMeasure>100 גרם</UnitMeasure>
      <BisWeighted>0</BisWeighted>
      <QtyInPackage>1</QtyInPackage>
      <ItemPrice>4.90</ItemPrice>
      <UnitOfMeasurePrice>9.80</UnitOfMeasurePrice>
      <AllowDiscount>1</AllowDiscount>
      <itemStatus>1</itemStatus>
      <LastUpdateDate />
      <LastUpdateTime />
    </Product>
    <Product>
      <PriceUpdateDate>2020/04/30 07:49</PriceUpdateDate>
      <ItemCode>608614255511</ItemCode>
      <ItemType>0</ItemType>
      <ItemName>פופקורנס טעם גבינה 50 גר</ItemName>
      <ManufactureName>אבאל יזמות בעמ</ManufactureName>
      <ManufactureCountry />
      <ManufactureItemDescription />
      <UnitQty>יח`</UnitQty>
      <Quantity>0.50</Quantity>
      <UnitMeasure>100 גרם</UnitMeasure>
      <BisWeighted>0</BisWeighted>
      <QtyInPackage>1</QtyInPackage>
      <ItemPrice>4.90</ItemPrice>
      <UnitOfMeasurePrice>9.80</UnitOfMeasurePrice>
      <AllowDiscount>1</AllowDiscount>
      <itemStatus>1</itemStatus>
      <LastUpdateDate />
      <LastUpdateTime />
    </Product>
    <Product>
      <PriceUpdateDate>2020/04/30 07:49</PriceUpdateDate>
      <ItemCode>608614255528</ItemCode>
      <ItemType>0</ItemType>
      <ItemName>פופקורנס טעם גריל 50 גר</ItemName>
      <ManufactureName>אבאל יזמות בעמ</ManufactureName>
      <ManufactureCountry />
      <ManufactureItemDescription />
      <UnitQty>יח`</UnitQty>
      <Quantity>0.50</Quantity>
      <UnitMeasure>100 גרם</UnitMeasure>
      <BisWeighted>0</BisWeighted>
      <QtyInPackage>1</QtyInPackage>
      <ItemPrice>4.90</ItemPrice>
      <UnitOfMeasurePrice>9.80</UnitOfMeasurePrice>
      <AllowDiscount>1</AllowDiscount>
      <itemStatus>1</itemStatus>
      <LastUpdateDate />
      <LastUpdateTime />
    </Product>
    <Product>
      <PriceUpdateDate>2020/04/30 07:49</PriceUpdateDate>
      <ItemCode>608614255535</ItemCode>
      <ItemType>0</ItemType>
      <ItemName>פופקורנס קרמל מלוח 50 גר</ItemName>
      <ManufactureName>אבאל יזמות בעמ</ManufactureName>
      <ManufactureCountry />
      <ManufactureItemDescription />
      <UnitQty>יח`</UnitQty>
      <Quantity>0.50</Quantity>
      <UnitMeasure>100 גרם</UnitMeasure>
      <BisWeighted>0</BisWeighted>
      <QtyInPackage>1</QtyInPackage>
      <ItemPrice>4.90</ItemPrice>
      <UnitOfMeasurePrice>9.80</UnitOfMeasurePrice>
      <AllowDiscount>1</AllowDiscount>
      <itemStatus>1</itemStatus>
      <LastUpdateDate />
      <LastUpdateTime />
    </Product>
    <Product>
      <PriceUpdateDate>2018/05/09 16:26</PriceUpdateDate>
      <ItemCode>4600659010854</ItemCode>
      <ItemType>1</ItemType>
      <ItemName>וודקה סטוליצ`יניה (700 מל)</ItemName>
      <ManufactureName>הכרם - משקאות חריפים בעמ</ManufactureName>
      <ManufactureCountry />
      <ManufactureItemDescription />
      <UnitQty>יח`</UnitQty>
      <Quantity>7</Quantity>
      <UnitMeasure>100 מ"ל</UnitMeasure>
      <BisWeighted>0</BisWeighted>
      <QtyInPackage>1</QtyInPackage>
      <ItemPrice>81.50</ItemPrice>
      <UnitOfMeasurePrice>11.60</UnitOfMeasurePrice>
      <AllowDiscount>1</AllowDiscount>
      <itemStatus>1</itemStatus>
      <LastUpdateDate />
      <LastUpdateTime />
    </Product>
    <Product>
      <PriceUpdateDate>2020/01/09 16:40</PriceUpdateDate>
      <ItemCode>4603400000043</ItemCode>
      <ItemType>1</ItemType>
      <ItemName>וודקה רוסקי יורוסטנדרט (700 מל)</ItemName>
      <ManufactureName>יורוסטנדרט בעמ</ManufactureName>
      <ManufactureCountry />
      <ManufactureItemDescription />
      <UnitQty>יח`</UnitQty>
      <Quantity>7</Quantity>
      <UnitMeasure>100 מ"ל</UnitMeasure>
      <BisWeighted>0</BisWeighted>
      <QtyInPackage>1</QtyInPackage>
      <ItemPrice>59.90</ItemPrice>
      <UnitOfMeasurePrice>8.51</UnitOfMeasurePrice>
      <AllowDiscount>1</AllowDiscount>
      <itemStatus>1</itemStatus>
      <LastUpdateDate />
      <LastUpdateTime />
    </Product>
    <Product>
      <PriceUpdateDate>2018/10/17 15:30</PriceUpdateDate>
      <ItemCode>5701932026964</ItemCode>
      <ItemType>1</ItemType>
      <ItemName>הוט פופ 600 גר`</ItemName>
      <ManufactureName>ליימן שליסל בעמ</ManufactureName>
      <ManufactureCountry />
      <ManufactureItemDescription />
      <UnitQty>יח`</UnitQty>
      <Quantity>1.50</Quantity>
      <UnitMeasure>100 מ"ל</UnitMeasure>
      <BisWeighted>0</BisWeighted>
      <QtyInPackage>1</QtyInPackage>
      <ItemPrice>16.90</ItemPrice>
      <UnitOfMeasurePrice>11.27</UnitOfMeasurePrice>
      <AllowDiscount>1</AllowDiscount>
      <itemStatus>1</itemStatus>
      <LastUpdateDate />
      <LastUpdateTime />
    </Product>
    <Product>
      <PriceUpdateDate>2018/10/17 15:30</PriceUpdateDate>
      <ItemCode>5701932026971</ItemCode>
      <ItemType>1</ItemType>
      <ItemName>הוט פופ חמאה 600 גר`</ItemName>
      <ManufactureName>ליימן שליסל בעמ</ManufactureName>
      <ManufactureCountry />
      <ManufactureItemDescription />
      <UnitQty>יח`</UnitQty>
      <Quantity>6</Quantity>
      <UnitMeasure>100 גרם</UnitMeasure>
      <BisWeighted>0</BisWeighted>
      <QtyInPackage>1</QtyInPackage>
      <ItemPrice>16.90</ItemPrice>
      <UnitOfMeasurePrice>2.82</UnitOfMeasurePrice>
      <AllowDiscount>1</AllowDiscount>
      <itemStatus>1</itemStatus>
      <LastUpdateDate />
      <LastUpdateTime />
    </Product>
    <Product>
      <PriceUpdateDate>2018/10/17 15:30</PriceUpdateDate>
      <ItemCode>5701932026995</ItemCode>
      <ItemType>1</ItemType>
      <ItemName>הוט פופ לייט 600גר`</ItemName>
      <ManufactureName>ליימן שליסל בעמ</ManufactureName>
      <ManufactureCountry />
      <ManufactureItemDescription />
      <UnitQty>יח`</UnitQty>
      <Quantity>6</Quantity>
      <UnitMeasure>100 גרם</UnitMeasure>
      <BisWeighted>0</BisWeighted>
      <QtyInPackage>1</QtyInPackage>
      <ItemPrice>16.90</ItemPrice>
      <UnitOfMeasurePrice>2.82</UnitOfMeasurePrice>
      <AllowDiscount>1</AllowDiscount>
      <itemStatus>1</itemStatus>
      <LastUpdateDate />
      <LastUpdateTime />
    </Product>
    <Product>
      <PriceUpdateDate>2018/10/17 15:30</PriceUpdateDate>
      <ItemCode>5706516031358</ItemCode>
      <ItemType>1</ItemType>
      <ItemName>הוט פופ 600 גר`</ItemName>
      <ManufactureName>ליימן שליסל בעמ</ManufactureName>
      <ManufactureCountry />
      <ManufactureItemDescription />
      <UnitQty>יח`</UnitQty>
      <Quantity>6</Quantity>
      <UnitMeasure>100 גרם</UnitMeasure>
      <BisWeighted>0</BisWeighted>
      <QtyInPackage>1</QtyInPackage>
      <ItemPrice>16.90</ItemPrice>
      <UnitOfMeasurePrice>2.82</UnitOfMeasurePrice>
      <AllowDiscount>1</AllowDiscount>
      <itemStatus>1</itemStatus>
      <LastUpdateDate />
      <LastUpdateTime />
    </Product>
    <Product>
      <PriceUpdateDate>2018/07/24 10:20</PriceUpdateDate>
      <ItemCode>7290000484747</ItemCode>
      <ItemType>1</ItemType>
      <ItemName>עלית הארק יקב הגליל (700 מל)</ItemName>
      <ManufactureName>יקב הגליל שיווק בעמ</ManufactureName>
      <ManufactureCountry />
      <ManufactureItemDescription />
      <UnitQty>יח`</UnitQty>
      <Quantity>7.50</Quantity>
      <UnitMeasure>100 מ"ל</UnitMeasure>
      <BisWeighted>0</BisWeighted>
      <QtyInPackage>1</QtyInPackage>
      <ItemPrice>59.90</ItemPrice>
      <UnitOfMeasurePrice>7.95</UnitOfMeasurePrice>
      <AllowDiscount>1</AllowDiscount>
      <itemStatus>1</itemStatus>
      <LastUpdateDate />
      <LastUpdateTime />
    </Product>
    <Product>
      <PriceUpdateDate>2020/04/30 07:49</PriceUpdateDate>
      <ItemCode>7290014947108</ItemCode>
      <ItemType>1</ItemType>
      <ItemName>זן בר פריכיות כוסמין ללא מלח 120 גר</ItemName>
      <ManufactureName>אבאל יזמות בעמ</ManufactureName>
      <ManufactureCountry />
      <ManufactureItemDescription />
      <UnitQty>יח`</UnitQty>
      <Quantity>1.20</Quantity>
      <UnitMeasure>100 גרם</UnitMeasure>
      <BisWeighted>0</BisWeighted>
      <QtyInPackage>1</QtyInPackage>
      <ItemPrice>7.90</ItemPrice>
      <UnitOfMeasurePrice>6.58</UnitOfMeasurePrice>
      <AllowDiscount>1</AllowDiscount>
      <itemStatus>1</itemStatus>
      <LastUpdateDate />
      <LastUpdateTime />
    </Product>
    <Product>
      <PriceUpdateDate>2020/04/30 07:49</PriceUpdateDate>
      <ItemCode>7290014947115</ItemCode>
      <ItemType>1</ItemType>
      <ItemName>זן בר פריכיות כוסמת עם מלח 120 גר</ItemName>
      <ManufactureName>אבאל יזמות בעמ</ManufactureName>
      <ManufactureCountry />
      <ManufactureItemDescription />
      <UnitQty>יח`</UnitQty>
      <Quantity>1.20</Quantity>
      <UnitMeasure>100 גרם</UnitMeasure>
      <BisWeighted>0</BisWeighted>
      <QtyInPackage>1</QtyInPackage>
      <ItemPrice>7.90</ItemPrice>
      <UnitOfMeasurePrice>6.58</UnitOfMeasurePrice>
      <AllowDiscount>1</AllowDiscount>
      <itemStatus>1</itemStatus>
      <LastUpdateDate />
      <LastUpdateTime />
    </Product>
    <Product>
      <PriceUpdateDate>2020/04/30 07:49</PriceUpdateDate>
      <ItemCode>7290014947122</ItemCode>
      <ItemType>1</ItemType>
      <ItemName>זן בר פריכיות כוסמת ללא מלח 120 גר</ItemName>
      <ManufactureName>אבאל יזמות בעמ</ManufactureName>
      <ManufactureCountry />
      <ManufactureItemDescription />
      <UnitQty>יח`</UnitQty>
      <Quantity>1.20</Quantity>
      <UnitMeasure>100 גרם</UnitMeasure>
      <BisWeighted>0</BisWeighted>
      <QtyInPackage>1</QtyInPackage>
      <ItemPrice>7.90</ItemPrice>
      <UnitOfMeasurePrice>6.58</UnitOfMeasurePrice>
      <AllowDiscount>1</AllowDiscount>
      <itemStatus>1</itemStatus>
      <LastUpdateDate />
      <LastUpdateTime />
    </Product>
    <Product>
      <PriceUpdateDate>2020/04/30 07:49</PriceUpdateDate>
      <ItemCode>7290014947139</ItemCode>
      <ItemType>1</ItemType>
      <ItemName>זן בר פריכיות תירס עם מלח 120 גר</ItemName>
      <ManufactureName>אבאל יזמות בעמ</ManufactureName>
      <ManufactureCountry />
      <ManufactureItemDescription />
      <UnitQty>יח`</UnitQty>
      <Quantity>1.20</Quantity>
      <UnitMeasure>100 גרם</UnitMeasure>
      <BisWeighted>0</BisWeighted>
      <QtyInPackage>1</QtyInPackage>
      <ItemPrice>7.90</ItemPrice>
      <UnitOfMeasurePrice>6.58</UnitOfMeasurePrice>
      <AllowDiscount>1</AllowDiscount>
      <itemStatus>1</itemStatus>
      <LastUpdateDate />
      <LastUpdateTime />
    </Product>
    <Product>
      <PriceUpdateDate>2018/05/09 22:00</PriceUpdateDate>
      <ItemCode>7290104727726</ItemCode>
      <ItemType>1</ItemType>
      <ItemName>שוקולד מריר עלית (100x5 גרם)</ItemName>
      <ManufactureName>שטראוס גרופ בעמ</ManufactureName>
      <ManufactureCountry />
      <ManufactureItemDescription />
      <UnitQty>יח`</UnitQty>
      <Quantity>5</Quantity>
      <UnitMeasure>100 גרם</UnitMeasure>
      <BisWeighted>0</BisWeighted>
      <QtyInPackage>1</QtyInPackage>
      <ItemPrice>24.40</ItemPrice>
      <UnitOfMeasurePrice>4.88</UnitOfMeasurePrice>
      <AllowDiscount>1</AllowDiscount>
      <itemStatus>1</itemStatus>
      <LastUpdateDate />
      <LastUpdateTime />
    </Product>
    <Product>
      <PriceUpdateDate>2018/05/09 22:00</PriceUpdateDate>
      <ItemCode>7290104729492</ItemCode>
      <ItemType>1</ItemType>
      <ItemName>שוקולד פרה חלב עלית (100x5 גרם)</ItemName>
      <ManufactureName>שטראוס גרופ בעמ</ManufactureName>
      <ManufactureCountry />
      <ManufactureItemDescription />
      <UnitQty>יח`</UnitQty>
      <Quantity>5</Quantity>
      <UnitMeasure>100 גרם</UnitMeasure>
      <BisWeighted>0</BisWeighted>
      <QtyInPackage>1</QtyInPackage>
      <ItemPrice>24.40</ItemPrice>
      <UnitOfMeasurePrice>4.88</UnitOfMeasurePrice>
      <AllowDiscount>1</AllowDiscount>
      <itemStatus>1</itemStatus>
      <LastUpdateDate />
      <LastUpdateTime />
    </Product>
    <Product>
      <PriceUpdateDate>2019/03/03 08:36</PriceUpdateDate>
      <ItemCode>7290105500151</ItemCode>
      <ItemType>1</ItemType>
      <ItemName>וודקה פינלנדיה 700 מל</ItemName>
      <ManufactureName>מ. אקרמן בעמ</ManufactureName>
      <ManufactureCountry />
      <ManufactureItemDescription />
      <UnitQty>יח`</UnitQty>
      <Quantity>7</Quantity>
      <UnitMeasure>100 מ"ל</UnitMeasure>
      <BisWeighted>0</BisWeighted>
      <QtyInPackage>1</QtyInPackage>
      <ItemPrice>67.90</ItemPrice>
      <UnitOfMeasurePrice>9.66</UnitOfMeasurePrice>
      <AllowDiscount>1</AllowDiscount>
      <itemStatus>1</itemStatus>
      <LastUpdateDate />
      <LastUpdateTime />
    </Product>
  </Products>
</Prices>